langtrace/__init__.py
langtrace/trace_attributes/__init__.py
langtrace/trace_attributes/models/__init__.py
langtrace/trace_attributes/models/database_span_attributes.py
langtrace/trace_attributes/models/framework_span_attributes.py
langtrace/trace_attributes/models/llm_span_attributes.py
trace_attributes-7.2.0.dist-info/LICENSE
trace_attributes-7.2.0.dist-info/METADATA
trace_attributes-7.2.0.dist-info/WHEEL
trace_attributes-7.2.0.dist-info/top_level.txt
trace_attributes-7.2.0.dist-info/RECORD
