Metadata-Version: 2.2
Name: trace-attributes
Version: 7.2.0
Summary: LangTrace - Trace Attributes
Home-page: https://github.com/Scale3-Labs/langtrace-trace-attributes
Author: Karthik Kalyanaraman
Author-email: karthik@scale3labs.com
Classifier: Programming Language :: Python :: 3
Classifier: License :: OSI Approved :: MIT License
Classifier: Operating System :: OS Independent
Requires-Python: >=3.6
License-File: LICENSE
Requires-Dist: pydantic>=1.8
Dynamic: author
Dynamic: author-email
Dynamic: classifier
Dynamic: description
Dynamic: description-content-type
Dynamic: home-page
Dynamic: requires-dist
Dynamic: requires-python
Dynamic: summary
